docx_merge/__init__.py
docx_merge/index.py
docx_merge/utils/__init__.py
docx_merge/utils/merger.py
docx_merge/utils/xml.py
docx_merge_xml-0.1.1.dist-info/LICENSE
docx_merge_xml-0.1.1.dist-info/METADATA
docx_merge_xml-0.1.1.dist-info/WHEEL
docx_merge_xml-0.1.1.dist-info/RECORD
