Metadata-Version: 2.3
Name: docx-merge-xml
Version: 0.1.1
Summary: A fast Python library for merging two Microsoft Word (.docx) documents into one.
License: MIT
Keywords: docx,merge,fast,xml,zip,office
Author: Benedicte Giraud
Author-email: benegir@gmail.com
Requires-Python: >=3.11
Classifier: License :: OSI Approved :: MIT License
Classifier: Programming Language :: Python :: 3
Classifier: Programming Language :: Python :: 3.11
Classifier: Programming Language :: Python :: 3.12
Classifier: Programming Language :: Python :: 3.13
Requires-Dist: lxml (>=5.4.0,<6.0.0)
Project-URL: Documentation, https://github.com/BenedicteGiraud/docx-merge-py
Project-URL: Homepage, https://github.com/BenedicteGiraud/docx-merge-py
Project-URL: Repository, https://github.com/BenedicteGiraud/docx-merge-py
Project-URL: issues, https://github.com/BenedicteGiraud/docx-merge-py/issues
